pulumi_zpa
