Metadata-Version: 2.1
Name: pulumi-zpa
Version: 0.0.2
Summary: A Pulumi package for creating and managing Zscaler Private Access (ZPA) cloud resources.
Home-page: https://www.zscaler.com
License: MIT
Project-URL: Repository, https://github.com/zscaler/pulumi-zpa
Keywords: pulumi zpa zscaler category/cloud
Platform: UNKNOWN
Requires-Python: >=3.7
